stadium/__init__.py
stadium/_version.py
stadium-0.0.1.dist-info/METADATA
stadium-0.0.1.dist-info/WHEEL
stadium-0.0.1.dist-info/top_level.txt
stadium-0.0.1.dist-info/RECORD
